justscheduleit-0.2.0.dist-info/METADATA
justscheduleit-0.2.0.dist-info/WHEEL
justscheduleit-0.2.0.dist-info/entry_points.txt
justscheduleit-0.2.0.dist-info/licenses/LICENSE
justscheduleit/__init__.py
justscheduleit/_utils.py
justscheduleit/_version.py
justscheduleit/cond/__init__.py
justscheduleit/cond/_core.py
justscheduleit/cond/cron.py
justscheduleit/cond/stream.py
justscheduleit/hosting.py
justscheduleit/http.py
justscheduleit/py.typed
justscheduleit/scheduler.py
justscheduleit-0.2.0.dist-info/RECORD
